{"hash":"67914fd947c86ec6cef518fc9b753f3d959daea2","data":{"labInstructions":{"id":"2-1","step":1,"lab":2,"title":"Lab 2","content":"<h2 id=\"page1html\"><a href=\"#page1html\" aria-hidden=\"true\"><span class=\"icon icon-link\"></span></a>page1.html</h2>\n<p>For page1.html, create eight flex containers. Each container will contains flex items that are 200px tall. Each flex item should also have 10px margin on all sides. Refer to the image below for the final mockup of how the completed page should look</p>\n<ol>\n<li>Flex Container 1 (Blue): There should be two flex items, equal in size, taking up all available space.</li>\n<li>Flex Container 2 (Red): There should be three flex items in this container. The first and the last should be equal in size, while the middle item is twice their size.</li>\n<li>Flex Container 3 (Purple): Similar to container 2, except the first and last should be twice the size of the middle item.</li>\n<li>Flex Container 4 (Green): Each flex item should take up 1/3 of the available space. The first one should be positioned on the left side of the container, and the second on the right.</li>\n<li>Flex Container 5 (Tan): Each flex item should take up 1/3 of the available space. They should be positioned in the center horizontally</li>\n<li>Flex Container 6 (Slate Gray): Each flex item should take up 1/4 of the available space. The space between each flex item should be double the space on the inside edges of the flex container.</li>\n<li>Flex Container 7 (Sea Green): Each flex item should take up 1/6 of the available space. They should be aligned on the right side of the flex container.</li>\n<li>Flex Container 8 (Yellow): Each flex item should take up 1/4 of the available space. The first two items should be positioned on the left side of the container, the third element on the right.</li>\n</ol>\n<p>Mockup</p>\n<p><img src=\"/lab2/page1.png\" alt=\"Mockup\"></p>\n","path":"/lab/2/1/","start":false,"last":false}},"context":{}}